README.rst
setup.py
moedj.egg-info/PKG-INFO
moedj.egg-info/SOURCES.txt
moedj.egg-info/dependency_links.txt
moedj.egg-info/entry_points.txt
moedj.egg-info/not-zip-safe
moedj.egg-info/requires.txt
moedj.egg-info/top_level.txt
moedjpack/__init__.py
moedjpack/manage.py
moedjpack/run.py
moedjpack/auth/__init__.py
moedjpack/auth/admin.py
moedjpack/auth/models.py
moedjpack/auth/tests.py
moedjpack/auth/views.py
moedjpack/forbidden/__init__.py
moedjpack/forbidden/admin.py
moedjpack/forbidden/models.py
moedjpack/forbidden/tests.py
moedjpack/forbidden/views.py
moedjpack/moedj/__init__.py
moedjpack/moedj/settings.py
moedjpack/moedj/urls.py
moedjpack/moedj/wsgi.py
moedjpack/moepad/__init__.py
moedjpack/moepad/mpcelery.py
moedjpack/moepad/mpconf.py
moedjpack/moepad/mpdefs.py
moedjpack/moepad/mptask.py
moedjpack/moepad/mputils.py
moedjpack/moepad/showstatus.py
moedjpack/moepad/update.py
moedjpack/moepad/weibo.py
moedjpack/moepad/weibowrapper.py
moedjpack/moewiki/__init__.py
moedjpack/moewiki/admin.py
moedjpack/moewiki/feedparser.py
moedjpack/moewiki/forms.py
moedjpack/moewiki/models.py
moedjpack/moewiki/tests.py
moedjpack/moewiki/views.py
moedjpack/qqweibo/__init__.py
moedjpack/qqweibo/api.py
moedjpack/qqweibo/auth.py
moedjpack/qqweibo/binder.py
moedjpack/qqweibo/cache.py
moedjpack/qqweibo/compat.py
moedjpack/qqweibo/error.py
moedjpack/qqweibo/models.py
moedjpack/qqweibo/oauth.py
moedjpack/qqweibo/parsers.py
moedjpack/qqweibo/utils.py
moedjpack/static/css/bootstrap-responsive.css
moedjpack/static/css/bootstrap-responsive.min.css
moedjpack/static/css/bootstrap-tagsinput.css
moedjpack/static/css/bootstrap.css
moedjpack/static/css/bootstrap.min.css
moedjpack/static/css/docs.css
moedjpack/static/css/mp.css
moedjpack/static/img/glyphicons-halflings-white.png
moedjpack/static/img/glyphicons-halflings.png
moedjpack/static/img/s24510739.jpg
moedjpack/static/js/application.js
moedjpack/static/js/bootstrap-affix.js
moedjpack/static/js/bootstrap-alert.js
moedjpack/static/js/bootstrap-button.js
moedjpack/static/js/bootstrap-carousel.js
moedjpack/static/js/bootstrap-collapse.js
moedjpack/static/js/bootstrap-dropdown.js
moedjpack/static/js/bootstrap-modal.js
