Metadata-Version: 1.1
Name: moedj
Version: 0.6.0.1
Summary: A simple weibo bot for zh.moegirl.org
Home-page: https://github.com/deloeating/moedj
Author: delo
Author-email: deloeating@gmail.com
License: MIT
Platform: linux
Classifier: Programming Language :: Python
Classifier: Development Status :: 4 - Beta
Classifier: Natural Language :: English
Classifier: Environment :: Web Environment
Classifier: Intended Audience :: Developers
Classifier: License :: OSI Approved :: MIT License
Classifier: Operating System :: POSIX :: Linux
Classifier: Topic :: Software Development :: Libraries :: Python Modules
Classifier: Topic :: Software Development :: Libraries :: Application Frameworks
Classifier: Topic :: Internet :: WWW/HTTP :: Dynamic Content
